requirements.txt
setup.py
print_imports/__init__.py
print_imports.egg-info/PKG-INFO
print_imports.egg-info/SOURCES.txt
print_imports.egg-info/dependency_links.txt
print_imports.egg-info/top_level.txt