Metadata-Version: 2.1
Name: print-imports
Version: 2020.7.1
Summary: Print every python import
Home-page: https://github.com/andrewp-as-is/print-imports.py
License: Unlicense
Keywords: import
Platform: UNKNOWN
Classifier: License :: Public Domain
Classifier: Operating System :: OS Independent
Classifier: Programming Language :: Python :: 3
